sparkypandy/__init__.py
sparkypandy/_column.py
sparkypandy/_dataframe.py
sparkypandy/_version.py
sparkypandy/testing.py
tests/__init__.py
tests/conftest.py
tests/test_column.py
tests/test_dataframe.py
tests/test_sparkypandy.py
tests/test_testing.py
sparkypandy-0.1.4.dist-info/LICENSE
sparkypandy-0.1.4.dist-info/METADATA
sparkypandy-0.1.4.dist-info/WHEEL
sparkypandy-0.1.4.dist-info/top_level.txt
sparkypandy-0.1.4.dist-info/RECORD
