Metadata-Version: 2.1
Name: sparkypandy
Version: 0.1.4
Summary: It's not spark, it's now pandas, it's just awkward...
Home-page: https://github.com/tpvasconcelos/sparkypandy
Author: Tomas Pereira de Vasconcelos
Author-email: tomasvasconcelos@gmail.com
License: Apache-2.0
Project-URL: Documentation, https://packaging.python.org/tutorials/distributing-packages/
Project-URL: Funding, https://donate.pypi.org
Project-URL: Source, https://github.com/sparkypandyasconcelos/sparkypandy
Project-URL: Tracker, https://github.com/sparkypandyasconcelos/sparkypandy/issues
Keywords: spark,pyspark,pandas,dataframe
Platform: UNKNOWN
Classifier: Development Status :: 1 - Planning
Classifier: Intended Audience :: Developers
Classifier: License :: OSI Approved :: Apache Software License
Classifier: Natural Language :: English
Classifier: Programming Language :: Python :: 3.7
Classifier: Programming Language :: Python :: 3.8
Classifier: Programming Language :: Python :: 3.9
Classifier: Programming Language :: Python :: Implementation :: CPython
Classifier: Topic :: Software Development
Classifier: Typing :: Typed
Requires-Python: <4.0,>=3.7.1
License-File: LICENSE
Requires-Dist: pandas (<2,>=1)
Requires-Dist: pyspark (<4,>=3)
Provides-Extra: dev
Requires-Dist: bumpversion (==0.6.0) ; extra == 'dev'
Requires-Dist: ipykernel (==5.5.5) ; extra == 'dev'
Requires-Dist: ipython (==7.21.0) ; extra == 'dev'
Requires-Dist: jupyterlab (==3.0.16) ; extra == 'dev'
Requires-Dist: sphinx (==3.5.1) ; extra == 'dev'
Requires-Dist: twine (==3.4.1) ; extra == 'dev'
Provides-Extra: tests
Requires-Dist: pytest (==6.2.2) ; extra == 'tests'
Requires-Dist: pytest-cov (==2.11.1) ; extra == 'tests'
Requires-Dist: tox (==3.22.0) ; extra == 'tests'
